aura_connect/__init__.py
aura_connect/client.py
aura_connect/publisher.py
aura_connect/query.py
aura_connect/subscriber.py
aura_connect-0.1.0.dist-info/METADATA
aura_connect-0.1.0.dist-info/WHEEL
aura_connect-0.1.0.dist-info/top_level.txt
aura_connect-0.1.0.dist-info/RECORD
