Metadata-Version: 2.4
Name: aura_connect
Version: 0.1.0
Summary: A simplified wrapper around the Zenoh SDK for pub/sub and request-reply patterns
Author: AuraSim Team
License: MIT
Classifier: Development Status :: 3 - Alpha
Classifier: Intended Audience :: Developers
Classifier: Programming Language :: Python :: 3
Classifier: Programming Language :: Python :: 3.10
Requires-Python: >=3.10
Requires-Dist: eclipse-zenoh==1.3.3
Provides-Extra: dev
Requires-Dist: pytest>=8.0.0; extra == "dev"
Requires-Dist: pytest-cov>=6.0.0; extra == "dev"
Requires-Dist: black>=25.0.0; extra == "dev"
Dynamic: requires-python
